xyzzzz/rest.py
PRACTICEEE-1.0.1.dist-info/LICENSE
PRACTICEEE-1.0.1.dist-info/METADATA
PRACTICEEE-1.0.1.dist-info/WHEEL
PRACTICEEE-1.0.1.dist-info/top_level.txt
PRACTICEEE-1.0.1.dist-info/RECORD
