Metadata-Version: 2.1
Name: PRACTICEEE
Version: 1.0.1
Summary: A Python package to get weather reports for any location.
Home-page: UNKNOWN
Author: Amreesh kumar
Author-email: starkk786@gmail.com
License: MIT
Platform: UNKNOWN
Classifier: License :: OSI Approved :: MIT License
Classifier: Programming Language :: Python :: 3
Classifier: Programming Language :: Python :: 3.7
